mangadlp/__about__.py
mangadlp/__main__.py
mangadlp/app.py
mangadlp/cache.py
mangadlp/cli.py
mangadlp/downloader.py
mangadlp/hooks.py
mangadlp/logger.py
mangadlp/metadata.py
mangadlp/models.py
mangadlp/utils.py
mangadlp/api/mangadex.py
mangadlp/metadata/ComicInfo_v2.0.xsd
manga_dlp-2.4.1.dist-info/METADATA
manga_dlp-2.4.1.dist-info/WHEEL
manga_dlp-2.4.1.dist-info/entry_points.txt
manga_dlp-2.4.1.dist-info/licenses/LICENSE
manga_dlp-2.4.1.dist-info/RECORD
