Metadata-Version: 2.1
Name: manga-dlp
Version: 2.4.1
Summary: A cli manga downloader
Project-URL: Homepage, https://github.com/olofvndrhr/manga-dlp
Project-URL: History, https://github.com/olofvndrhr/manga-dlp/commits/master
Project-URL: Tracker, https://github.com/olofvndrhr/manga-dlp/issues
Project-URL: Source, https://github.com/olofvndrhr/manga-dlp
Author-email: Ivan Schaller <ivan@schaller.sh>
License-Expression: MIT
License-File: LICENSE
Keywords: downloader,manga,mangadex
Classifier: License :: OSI Approved :: MIT License
Classifier: Natural Language :: English
Classifier: Operating System :: OS Independent
Classifier: Programming Language :: Python :: 3.8
Classifier: Programming Language :: Python :: 3.9
Classifier: Programming Language :: Python :: 3.10
Classifier: Programming Language :: Python :: 3.11
Requires-Python: >=3.8
Requires-Dist: click-option-group>=0.5.5
Requires-Dist: click>=8.1.3
Requires-Dist: img2pdf>=0.4.4
Requires-Dist: loguru>=0.6.0
Requires-Dist: pytz==2022.1
Requires-Dist: requests>=2.28.0
Requires-Dist: xmltodict>=0.13.0
